spideymaps/__init__.py
spideymaps/spidey_atlas.py
spideymaps/spideymap.py
spideymaps/spideymaps_calculation.py
spideymaps/spideymaps_read.py
spideymaps/spideymaps_rendering.py
spideymaps-0.1.2.dist-info/LICENSE
spideymaps-0.1.2.dist-info/METADATA
spideymaps-0.1.2.dist-info/WHEEL
spideymaps-0.1.2.dist-info/top_level.txt
spideymaps-0.1.2.dist-info/RECORD
