Metadata-Version: 2.1
Name: spideymaps
Version: 0.1.2
Summary: For generating heat maps of single-molecule localization data in rod-shaped bacteria.
Author: Daniel Foust
Author-email: djfoust@umich.edu
Classifier: Programming Language :: Python :: 3
Classifier: Operating System :: OS Independent
License-File: LICENSE
Requires-Dist: h5py>=3.0.0
Requires-Dist: matplotlib
Requires-Dist: numpy
Requires-Dist: pandas
Requires-Dist: scipy
Requires-Dist: seaborn
Requires-Dist: shapely>=2.0.0
Requires-Dist: scikit-image
